basis/__init__.py
basis/cli/__init__.py
basis/cli/commands/__init__.py
basis/cli/commands/config.py
basis/cli/commands/create.py
basis/cli/commands/deploy.py
basis/cli/commands/list.py
basis/cli/commands/login.py
basis/cli/commands/logout.py
basis/cli/commands/pull.py
basis/cli/commands/trigger.py
basis/cli/commands/upload.py
basis/cli/config.py
basis/cli/helpers.py
basis/cli/main.py
basis/cli/services/__init__.py
basis/cli/services/accounts.py
basis/cli/services/api.py
basis/cli/services/auth.py
basis/cli/services/deploy.py
basis/cli/services/download.py
basis/cli/services/environments.py
basis/cli/services/graph.py
basis/cli/services/graph_components.py
basis/cli/services/graph_versions.py
basis/cli/services/list.py
basis/cli/services/login.py
basis/cli/services/logout.py
basis/cli/services/lookup.py
basis/cli/services/organizations.py
basis/cli/services/output.py
basis/cli/services/pagination.py
basis/cli/services/paths.py
basis/cli/services/pull.py
basis/cli/services/trigger.py
basis/cli/services/upload.py
basis/configuration/__init__.py
basis/configuration/edit.py
basis/helpers/__init__.py
basis/helpers/http.py
basis/node/__init__.py
basis/node/_methods.py
basis/node/node.py
basis_devkit-0.1.9.dist-info/entry_points.txt
basis_devkit-0.1.9.dist-info/LICENSE
basis_devkit-0.1.9.dist-info/WHEEL
basis_devkit-0.1.9.dist-info/METADATA
basis_devkit-0.1.9.dist-info/RECORD
