Metadata-Version: 2.1
Name: basis-devkit
Version: 0.1.9
Summary: Data pipelines from re-usable components
License: BSD-3-Clause
Author: AJ Alt
Author-email: aj@getbasis.com
Requires-Python: >=3.8,<4.0
Classifier: License :: OSI Approved :: BSD License
Classifier: Programming Language :: Python :: 3
Classifier: Programming Language :: Python :: 3.10
Classifier: Programming Language :: Python :: 3.8
Classifier: Programming Language :: Python :: 3.9
Requires-Dist: click (==8.0.4)
Requires-Dist: platformdirs (>=2.4.0,<3.0.0)
Requires-Dist: pydantic (>=1.8.1,<2.0.0)
Requires-Dist: rich (>=12.0.1,<13.0.0)
Requires-Dist: ruyaml (>=0.91.0,<0.92.0)
Requires-Dist: typer[all] (>=0.4.0,<0.5.0)
